ais/__init__.py
ais/cli/__init__.py
ais/cli/interactive.py
ais/cli/main.py
ais/core/__init__.py
ais/core/ai.py
ais/core/analysis.py
ais/core/config.py
ais/core/context.py
ais/core/database.py
ais/core/html_report.py
ais/core/report.py
ais/core/streaming.py
ais/shell/integration.sh
ais/ui/__init__.py
ais/ui/panels.py
ais/utils/__init__.py
ais_terminal-3.3.1.dist-info/METADATA
ais_terminal-3.3.1.dist-info/WHEEL
ais_terminal-3.3.1.dist-info/entry_points.txt
ais_terminal-3.3.1.dist-info/licenses/LICENSE
ais_terminal-3.3.1.dist-info/RECORD
