Metadata-Version: 2.4
Name: ais-terminal
Version: 3.3.1
Summary: 上下文感知的错误分析学习助手 - 让每次报错都是成长
Project-URL: Homepage, https://github.com/kangvcar/ais
Project-URL: Repository, https://github.com/kangvcar/ais
Project-URL: Documentation, https://github.com/kangvcar/ais/blob/main/docs/README.md
Project-URL: Issues, https://github.com/kangvcar/ais/issues
Project-URL: Changelog, https://github.com/kangvcar/ais/blob/main/docs/CHANGELOG.md
Author-email: AIS Team <ais@example.com>
Maintainer-email: AIS Team <ais@example.com>
License: MIT
License-File: LICENSE
Keywords: ai,assistant,automation,cli,error-analysis,shell,terminal
Classifier: Development Status :: 4 - Beta
Classifier: Environment :: Console
Classifier: Intended Audience :: Developers
Classifier: Intended Audience :: End Users/Desktop
Classifier: Intended Audience :: System Administrators
Classifier: License :: OSI Approved :: MIT License
Classifier: Operating System :: MacOS
Classifier: Operating System :: POSIX :: Linux
Classifier: Programming Language :: Python :: 3
Classifier: Programming Language :: Python :: 3.9
Classifier: Programming Language :: Python :: 3.10
Classifier: Programming Language :: Python :: 3.11
Classifier: Programming Language :: Python :: 3.12
Classifier: Topic :: Scientific/Engineering :: Artificial Intelligence
Classifier: Topic :: System :: Shells
Classifier: Topic :: System :: System Shells
Classifier: Topic :: Terminals
Classifier: Topic :: Utilities
Requires-Python: >=3.9
Requires-Dist: click>=8.0.0
Requires-Dist: httpx[socks]>=0.24.0
Requires-Dist: numpy>=1.20.0
Requires-Dist: plotly>=5.0.0
Requires-Dist: questionary>=2.0.0
Requires-Dist: rich>=13.0.0
Requires-Dist: sqlmodel>=0.0.14
Requires-Dist: toml>=0.10.2
Provides-Extra: all
Requires-Dist: black>=23.0.0; extra == 'all'
Requires-Dist: docker-compose>=1.29.0; extra == 'all'
Requires-Dist: docker>=6.0.0; extra == 'all'
Requires-Dist: flake8>=6.0.0; extra == 'all'
Requires-Dist: mypy>=1.0.0; extra == 'all'
Requires-Dist: pre-commit>=3.0.0; extra == 'all'
Requires-Dist: pytest-cov>=4.0.0; extra == 'all'
Requires-Dist: pytest>=7.0.0; extra == 'all'
Provides-Extra: dev
Requires-Dist: black>=23.0.0; extra == 'dev'
Requires-Dist: flake8>=6.0.0; extra == 'dev'
Requires-Dist: mypy>=1.0.0; extra == 'dev'
Requires-Dist: pre-commit>=3.0.0; extra == 'dev'
Requires-Dist: pytest-cov>=4.0.0; extra == 'dev'
Requires-Dist: pytest>=7.0.0; extra == 'dev'
Provides-Extra: docker
Requires-Dist: docker-compose>=1.29.0; extra == 'docker'
Requires-Dist: docker>=6.0.0; extra == 'docker'
Provides-Extra: html
